crawler/__init__.py
crawler/main.py
crawler/models.py
crawler/parse.py
crawler/storage.py
giga_crawler-0.1.0.dist-info/METADATA
giga_crawler-0.1.0.dist-info/WHEEL
giga_crawler-0.1.0.dist-info/entry_points.txt
giga_crawler-0.1.0.dist-info/RECORD
