Metadata-Version: 2.4
Name: giga_crawler
Version: 0.1.0
Summary: A tool for parsing Git repositories and markdown files.
Requires-Python: >=3.9
Requires-Dist: gitpython>=3.1.0
Requires-Dist: pydantic>=1.10
